x7/__init__.py
x7/x7/__init__.py
x7/x7/__version__.py
x7/x7/needs_test.py
x7-0.2.0.dist-info/LICENSE
x7-0.2.0.dist-info/METADATA
x7-0.2.0.dist-info/WHEEL
x7-0.2.0.dist-info/entry_points.txt
x7-0.2.0.dist-info/top_level.txt
x7-0.2.0.dist-info/RECORD
